{
	"classname": "CEconTool_DescTag",
	"classname_mangled": "_ZTV17CEconTool_DescTag",
	"members": [
		{
			"name": "CEconTool_DescTag::~CEconTool_DescTag()",
			"name_mangled": "_ZN17CEconTool_DescTagD0Ev"
		},
		{
			"name": "IEconTool::CanApplyTo(IEconItemInterface const*, IEconItemInterface const*) const",
			"name_mangled": "_ZNK9IEconTool10CanApplyToEPK18IEconItemInterfaceS2_"
		},
		{
			"name": "IEconTool::ShouldDisplayQuantity(IEconItemInterface const*) const",
			"name_mangled": "_ZNK9IEconTool21ShouldDisplayQuantityEPK18IEconItemInterface"
		},
		{
			"name": "IEconTool::RequiresToolEscrowPeriod() const",
			"name_mangled": "_ZNK9IEconTool24RequiresToolEscrowPeriodEv"
		},
		{
			"name": "IEconTool::BFinishInitialization()",
			"name_mangled": "_ZN9IEconTool21BFinishInitializationEv"
		}
	]
}